airweave/__init__.py
airweave-0.0.0.dist-info/METADATA
airweave-0.0.0.dist-info/WHEEL
airweave-0.0.0.dist-info/top_level.txt
airweave-0.0.0.dist-info/RECORD
