Metadata-Version: 2.1
Name: airweave
Version: 0.0.0
Summary: Coming soon
Author-email: Lennert Jansen <lennert@neena.io>
